{
  "lang": "en",
  "articles": [
    {
      "title": "Main Page",
      "views": 0
    },
    {
      "title": "Special:Search",
      "views": 0
    },
    {
      "title": "The Odyssey (2026 film)",
      "views": 0
    },
    {
      "title": "Wikipedia:Featured pictures",
      "views": 0
    },
    {
      "title": "Odyssey",
      "views": 0
    },
    {
      "title": "2026 FIFA World Cup",
      "views": 0
    },
    {
      "title": "Kylian Mbappé",
      "views": 0
    },
    {
      "title": "Sonam Wangchuk",
      "views": 0
    },
    {
      "title": "Lamine Yamal",
      "views": 0
    },
    {
      "title": "List of FIFA World Cup top goalscorers",
      "views": 0
    },
    {
      "title": "Lionel Messi",
      "views": 0
    },
    {
      "title": "Christopher Nolan",
      "views": 0
    },
    {
      "title": "Jude Bellingham",
      "views": 0
    },
    {
      "title": "Obsession (2025 film)",
      "views": 0
    },
    {
      "title": "Bukayo Saka",
      "views": 0
    }
  ]
}
